pycomms_pay/__init__.py
pycomms_pay/email_package/__init__.py
pycomms_pay/email_package/fetching.py
pycomms_pay/email_package/gmail.py
pycomms_pay/email_package/send.py
pycomms_pay/email_package/trash.py
pycomms_pay/payment_package/__init__.py
pycomms_pay/payment_package/config.py
pycomms_pay/payment_package/momo.py
pycomms_pay/payment_package/paypal.py
pycomms_pay/payment_package/paystack.py
pycomms_pay/payment_package/req_body_paypal.py
pycomms_pay/payment_package/req_body_paystack.py
pycomms_pay/sms_package/__init__.py
pycomms_pay/sms_package/config.py
pycomms_pay/sms_package/sms.py
pycomms_pay-1.1.2.dist-info/METADATA
pycomms_pay-1.1.2.dist-info/WHEEL
pycomms_pay-1.1.2.dist-info/top_level.txt
pycomms_pay-1.1.2.dist-info/RECORD
