Metadata-Version: 2.1
Name: pycomms_pay
Version: 1.1.2
Summary: A package for seamless Email, SMS and Payment Packages Integration
Home-page: https://github.com/sbarhin/Python_Package
Author: Shaukat Bint Arhin
Author-email: shaubint123@gmail.com
License: MIT
Classifier: Programming Language :: Python :: 3
Classifier: Operating System :: OS Independent
Requires-Python: >=3.6
Requires-Dist: google-auth
Requires-Dist: google-auth-oauthlib
Requires-Dist: google-auth-httplib2
Requires-Dist: google-api-python-client
Requires-Dist: requests
